{
	"configurations" : 
	[
		{
			"directories" : 
			[
				{
					"build" : ".",
					"jsonFile" : "directory-.-Debug-d0094a50bb2071803777.json",
					"minimumCMakeVersion" : 
					{
						"string" : "3.27"
					},
					"projectIndex" : 0,
					"source" : ".",
					"targetIndexes" : 
					[
						0
					]
				}
			],
			"name" : "Debug",
			"projects" : 
			[
				{
					"directoryIndexes" : 
					[
						0
					],
					"name" : "mark_sweep_gc",
					"targetIndexes" : 
					[
						0
					]
				}
			],
			"targets" : 
			[
				{
					"directoryIndex" : 0,
					"id" : "mark_sweep_gc::@6890427a1f51a3e7e1df",
					"jsonFile" : "target-mark_sweep_gc-Debug-bd3b70e33a4cff43b7d4.json",
					"name" : "mark_sweep_gc",
					"projectIndex" : 0
				}
			]
		}
	],
	"kind" : "codemodel",
	"paths" : 
	{
		"build" : "C:/Users/adria/CLionProjects/mark_sweep_gc/cmake-build-debug",
		"source" : "C:/Users/adria/CLionProjects/mark_sweep_gc"
	},
	"version" : 
	{
		"major" : 2,
		"minor" : 6
	}
}
